propo/__init__.py
propo/common.py
propo/propo.py
propo-0.0.2.dist-info/LICENSE
propo-0.0.2.dist-info/METADATA
propo-0.0.2.dist-info/WHEEL
propo-0.0.2.dist-info/entry_points.txt
propo-0.0.2.dist-info/top_level.txt
propo-0.0.2.dist-info/RECORD
